{
  "$schema": "https://developer.microsoft.com/json-schemas/fabric/item/report/definition/visualContainer/2.5.0/schema.json",
  "name": "9fe6fb22c97ebec1bfd4",
  "position": {
    "x": 596.74229758777165,
    "y": 0,
    "z": 6000,
    "height": 59.918796274181993,
    "width": 379.07809887747794,
    "tabOrder": 6000
  },
  "visual": {
    "visualType": "textbox",
    "objects": {
      "general": [
        {
          "properties": {
            "paragraphs": [
              {
                "textRuns": [
                  {
                    "value": "RAPPORT FACTURATION",
                    "textStyle": {
                      "fontWeight": "bold",
                      "fontFamily": "DIN",
                      "fontSize": "28pt",
                      "color": "#12239e"
                    }
                  }
                ],
                "horizontalTextAlignment": "center"
              }
            ]
          }
        }
      ]
    },
    "visualContainerObjects": {
      "background": [
        {
          "properties": {
            "show": {
              "expr": {
                "Literal": {
                  "Value": "false"
                }
              }
            }
          }
        }
      ]
    },
    "drillFilterOtherVisuals": true
  }
}